isolated_environment/__init__.py
isolated_environment/api.py
isolated_environment/cli.py
isolated_environment/assets/example.txt
isolated_environment-2.0.5.dist-info/LICENSE
isolated_environment-2.0.5.dist-info/METADATA
isolated_environment-2.0.5.dist-info/WHEEL
isolated_environment-2.0.5.dist-info/top_level.txt
isolated_environment-2.0.5.dist-info/RECORD
