Metadata-Version: 2.1
Name: isolated-environment
Version: 2.0.5
Summary: Like Pipx, but allows creation of a virtual environment then populating it.
Home-page: https://github.com/zackees/isolated-environment
Maintainer: Zachary Vorhies
License: BSD 3-Clause License
Keywords: template-python-cmd
Classifier: Programming Language :: Python :: 3
Requires-Python: >=3.10
License-File: LICENSE
Requires-Dist: wheel
Requires-Dist: filelock
Requires-Dist: setuptools
